nashi/__init__.py
nashi/books.py
nashi/database.py
nashi/default_settings.py
nashi/image.py
nashi/import_from_larex.py
nashi/import_from_pagexml.py
nashi/models.py
nashi/navigation.py
nashi/tasks.py
nashi/views.py
nashi/static/editor.css
nashi/static/editor.js
nashi/templates/_compareresults.html
nashi/templates/_searchresults.html
nashi/templates/base.html
nashi/templates/bootstrapexample.html
nashi/templates/change_password.html
nashi/templates/chartable.html
nashi/templates/editor.html
nashi/templates/forgot_password.html
nashi/templates/index.html
nashi/templates/login.html
nashi/templates/reset_password.html
nashi/templates/selectlarex.html
nashi/templates/textcheck.html
nashi/templates/textedit.html
nashi-0.0.46.dist-info/LICENSE
nashi-0.0.46.dist-info/METADATA
nashi-0.0.46.dist-info/WHEEL
nashi-0.0.46.dist-info/entry_points.txt
nashi-0.0.46.dist-info/top_level.txt
nashi-0.0.46.dist-info/RECORD
