Metadata-Version: 2.1
Name: nashi
Version: 0.0.46
Summary: A webapp for the transcription of scanned pages
Home-page: https://github.com/andbue/nashi
Author: Andreas Büttner
Author-email: andreas.buettner@uni-wuerzburg.de
License: GPL_v3.0
Classifier: Programming Language :: Python :: 3
Classifier: Programming Language :: JavaScript
Classifier: Development Status :: 3 - Alpha
Classifier: Framework :: Flask
Classifier: License :: OSI Approved :: GNU General Public License v3 (GPLv3)
Requires-Python: >=3
License-File: ./LICENSE
Requires-Dist: sqlalchemy
Requires-Dist: flask-security
Requires-Dist: bcrypt
Requires-Dist: flask-bootstrap
Requires-Dist: flask-nav
Requires-Dist: celery
Requires-Dist: redis
Requires-Dist: lxml
Requires-Dist: pillow
Requires-Dist: krakensegment
Requires-Dist: scikit-image
Requires-Dist: Flask
Requires-Dist: email-validator
